texproject/__init__.py
texproject/__main__.py
texproject/base.py
texproject/command.py
texproject/control.py
texproject/error.py
texproject/filesystem.py
texproject/git.py
texproject/output.py
texproject/template.py
texproject/term.py
texproject/utils.py
texproject/defaults/__init__.py
texproject/defaults/config.toml
texproject/defaults/template.toml
texproject/templates/__init__.py
texproject/templates/arxiv_autotex.txt
texproject/templates/base.tex
texproject/templates/bibinfo.tex
texproject/templates/bibliography.tex
texproject/templates/build.yaml
texproject/templates/classinfo.tex
texproject/templates/gitignore
texproject/templates/pre-commit
texproject/templates/project_macro_file.tex
texproject-0.8.8.dist-info/LICENSE
texproject-0.8.8.dist-info/METADATA
texproject-0.8.8.dist-info/WHEEL
texproject-0.8.8.dist-info/entry_points.txt
texproject-0.8.8.dist-info/top_level.txt
texproject-0.8.8.dist-info/RECORD
