Metadata-Version: 2.1
Name: texproject
Version: 0.8.8
Summary: An automatic LaTeX project manager.
Home-page: https://github.com/alexrutar/texproject
Author: Alex Rutar
Author-email: a@rutar.org
Classifier: Development Status :: 3 - Alpha
Classifier: Programming Language :: Python :: 3.10
Classifier: License :: OSI Approved :: MIT License
Classifier: Operating System :: OS Independent
Requires-Python: >=3.11.0
License-File: LICENSE
Requires-Dist: tomli-w (>=1.0.0)
Requires-Dist: Jinja2 (>=3.1.2)
Requires-Dist: xdg-base-dirs (>=6.0.0)
Requires-Dist: click (>=8.1.3)
